MANIFEST.in
MIT-LICENSE.txt
README.rst
requirements.txt
setup.py
django_lets_go/__init__.py
django_lets_go/admin_custom_actions.py
django_lets_go/app_label_renamer.py
django_lets_go/big_integer_field.py
django_lets_go/common_functions.py
django_lets_go/custom_xml_emitter.py
django_lets_go/filter_persist_middleware.py
django_lets_go/intermediate_model_base_class.py
django_lets_go/language_field.py
django_lets_go/only_one_task.py
django_lets_go/utils.py
django_lets_go/widgets.py
django_lets_go.egg-info/PKG-INFO
django_lets_go.egg-info/SOURCES.txt
django_lets_go.egg-info/dependency_links.txt
django_lets_go.egg-info/not-zip-safe
django_lets_go.egg-info/top_level.txt
django_lets_go/templatetags/__init__.py
django_lets_go/templatetags/common_tags.py