Metadata-Version: 1.1
Name: django-lets-go
Version: 2.9.2
Summary: Django helpers, goodies, mix of snippets, etc...
Home-page: http://github.com/areski/django-lets-go
Author: Belaid Arezqui
Author-email: areski@gmail.com
License: MIT License
Platform: UNKNOWN
Classifier: Development Status :: 5 - Production/Stable
Classifier: Environment :: Web Environment
Classifier: Framework :: Django
Classifier: Intended Audience :: Developers
Classifier: License :: OSI Approved :: MIT License
Classifier: Operating System :: OS Independent
Classifier: Programming Language :: Python
Classifier: Topic :: Software Development :: Libraries :: Python Modules
